meowsum/__init__.py
meowsum/__main__.py
meowsum/meow.py
meowsum-0.1.0.dist-info/METADATA
meowsum-0.1.0.dist-info/WHEEL
meowsum-0.1.0.dist-info/entry_points.txt
meowsum-0.1.0.dist-info/licenses/LICENSE
meowsum-0.1.0.dist-info/RECORD
