Metadata-Version: 2.4
Name: meowsum
Version: 0.1.0
Summary: Cat-sound lorem ipsum generator: meow, meeeow, meeeoooow.
Project-URL: Homepage, https://example.com/meowsum
Project-URL: Repository, https://example.com/meowsum/repo
Author: Meowsum Authors
License: MIT
License-File: LICENSE
Keywords: cats,generator,ipsum,lorem,meow,placeholder,text
Classifier: Development Status :: 3 - Alpha
Classifier: Environment :: Console
Classifier: Intended Audience :: Developers
Classifier: License :: OSI Approved :: MIT License
Classifier: Programming Language :: Python
Classifier: Programming Language :: Python :: 3
Classifier: Programming Language :: Python :: 3 :: Only
Classifier: Programming Language :: Python :: 3.8
Classifier: Programming Language :: Python :: 3.9
Classifier: Programming Language :: Python :: 3.10
Classifier: Programming Language :: Python :: 3.11
Classifier: Programming Language :: Python :: 3.12
Classifier: Topic :: Text Processing
Classifier: Topic :: Utilities
Requires-Python: >=3.8
